__init__.py
cycling_dynamics/__about__.py
cycling_dynamics/__init__.py
cycling_dynamics/calc.py
cycling_dynamics/critical_power.py
cycling_dynamics/dynamics.py
cycling_dynamics/load_data.py
cycling_dynamics/models.py
cycling_dynamics/plots.py
cycling_dynamics/segments.py
cycling_dynamics/surface.py
cycling_dynamics/temp_segments.py
cycling_dynamics-2025.4.1.dist-info/licenses/LICENSE.md
cycling_dynamics-2025.4.1.dist-info/METADATA
cycling_dynamics-2025.4.1.dist-info/WHEEL
cycling_dynamics-2025.4.1.dist-info/top_level.txt
cycling_dynamics-2025.4.1.dist-info/RECORD
